MANIFEST.in
README.rst
setup.py
plone/__init__.py
plone.app.imagetile.egg-info/PKG-INFO
plone.app.imagetile.egg-info/SOURCES.txt
plone.app.imagetile.egg-info/dependency_links.txt
plone.app.imagetile.egg-info/entry_points.txt
plone.app.imagetile.egg-info/namespace_packages.txt
plone.app.imagetile.egg-info/not-zip-safe
plone.app.imagetile.egg-info/requires.txt
plone.app.imagetile.egg-info/top_level.txt
plone/app/__init__.py
plone/app/imagetile/__init__.py
plone/app/imagetile/configure.zcml
plone/app/imagetile/testing.py
plone/app/imagetile/tile.css
plone/app/imagetile/tile.js
plone/app/imagetile/tile.png
plone/app/imagetile/tile.pt
plone/app/imagetile/tile.py
plone/app/imagetile/tile.txt
plone/app/imagetile/profiles/default/cssregistry.xml
plone/app/imagetile/profiles/default/jsregistry.xml
plone/app/imagetile/profiles/default/metadata.xml
plone/app/imagetile/profiles/default/registry.xml
plone/app/imagetile/tests/__init__.py
plone/app/imagetile/tests/test_doctests.py