Metadata-Version: 1.0
Name: plone.app.imagetile
Version: 1.0
Summary: Image tile for deco UI
Home-page: https://github.com/plone/plone.app.imagetile
Author: Thomas Buchberger
Author-email: t.buchberger@4teamwork.ch
License: GPL
Keywords: plone deco tile
Platform: UNKNOWN
Classifier: Framework :: Plone
Classifier: Programming Language :: Python
